[
  {
    "id": "1a",
    "text":
      "Track Bond Conditions (complete, undamaged, ensures conductivity)",
    "answer": null,
    "note": ""
  },
  {
    "id": "1b",
    "text": "Track lead Conditions (complete, undamaged, secured)",
    "answer": null,
    "note": ""
  },
  {
    "id": "1c",
    "text":
      "Insulated joint Conditions (end post intact, tie plates clear, bolts tight, spikes reversed,), prevent current from flowing between rails separated by the insulation.",
    "answer": null,
    "note": ""
  },
  {
    "id": "1d",
    "text":
      "Detect a shunt of 0.06 ohm resistance when the shunt is connected across the track rails of any part of the circuit. Adjustment, Contamination of track circuit, signal in vicinity.",
    "answer": null,
    "note": ""
  },
  {
    "id": "1e",
    "text":
      "Provide a set of fouling wires that consist of at least two discrete conductors and must ensure proper operation of the track circuit when the circuit is shunted. Single duplex wire with single plug is not permitted",
    "answer": null,
    "note": ""
  },
  {
    "id": "1f",
    "text":
      "Track circuit Polarity (Staggered and in conformity to the design plan)",
    "answer": null,
    "note": ""
  },
  {
    "id": "2",
    "text": "Warning Time insufficient, or Approach Time Variance",
    "answer": null,
    "note": ""
  },
  {
    "id": "3",
    "text": "Bell operation, location and configuration",
    "answer": null,
    "note": ""
  },
  {
    "id": "4a",
    "text":
      "Gate Conditions (arm covers lane, gate light condition, reflecting tape)",
    "answer": null,
    "note": ""
  },
  {
    "id": "4b",
    "text":
      "Operation of gates (Begin its descent once the calculated gate arm clearance time has elapsed (min 3 sec), descent time horizontal within 10 and 15 sec , ascent time within 6 to 12 seconds)",
    "answer": null,
    "note": ""
  },
  {
    "id": "5a",
    "text": "Interconnection - Railway (preemption time, perform test) ",
    "answer": null,
    "note": ""
  },
  {
    "id": "5b",
    "text":
      "Interconnection - Road Authority (preemption time, perform test)",
    "answer": null,
    "note": ""
  },
  {
    "id": "6a",
    "text":
      "Cut-out Control Feature (equipped with a control feature to minimize the operation of the warning system where required)",
    "answer": null,
    "note": ""
  },
  {
    "id": "6b",
    "text":
      "Switch Circuit Controller Cut Out (cuts out only when the switch point is within one-half inch of full reverse position (when equipped))",
    "answer": null,
    "note": ""
  },
  {
    "id": "7a",
    "text":
      "Light Unit Condition (physical condition of light units, compare lens deflection with plans, note type)",
    "answer": null,
    "note": ""
  },
  {
    "id": "7b",
    "text":
      "Light Unit Configuration (light units cover all road approaches)",
    "answer": null,
    "note": ""
  },
  {
    "id": "7c",
    "text":
      "Light Alignment (all lights visible to the appropriate alignment point)",
    "answer": null,
    "note": ""
  },
  {
    "id": "7d",
    "text":
      "Visibility of Warning System From SSD (at least one set of lights are visible from SSD)",
    "answer": null,
    "note": ""
  },
  {
    "id": "7e",
    "text":
      "Light Unit Flash Rate & Operation (flash alternately and uniformly and at the prescribed flash rate)",
    "answer": null,
    "note": ""
  },
  {
    "id": "8a",
    "text": "Record of weekly tests (no missing or overdue tests)",
    "answer": null,
    "note": ""
  },
  {
    "id": "8b",
    "text":
      "Record of monthly, quarterly and semiannual tests (no missing or overdue tests)",
    "answer": null,
    "note": ""
  },
  {
    "id": "8c",
    "text": "Record of annual tests (no missing or overdue tests)",
    "answer": null,
    "note": ""
  },
  {
    "id": "8d",
    "text": "Record of two year tests (no missing or overdue tests)",
    "answer": null,
    "note": ""
  },
  {
    "id": "8e",
    "text": "Record of Four Year Tests (no missing or overdue tests)",
    "answer": null,
    "note": ""
  },
  {
    "id": "8f",
    "text": "Record of Ten Year Tests (no missing or overdue tests)",
    "answer": null,
    "note": ""
  },
  {
    "id": "9",
    "text":
      "Directional Stick Circuit (timing device, stick release, stick circuit indication)",
    "answer": null,
    "note": ""
  },
  {
    "id": "10a",
    "text":
      "Standby Battery Conditions (clean & free of corrosion, voltage reading taken pre/post 15 min power off)",
    "answer": null,
    "note": ""
  },
  {
    "id": "10b",
    "text":
      "AC Power and Components (phases consistent and equal under load)",
    "answer": null,
    "note": ""
  },
  {
    "id": "10c",
    "text": "Power Off Light (visible, functional)",
    "answer": null,
    "note": ""
  },
  {
    "id": "11",
    "text":
      "Battery Isolation Condition (no voltage potential between power supplies)",
    "answer": null,
    "note": ""
  },
  {
    "id": "12",
    "text":
      "Circuit Grounds (no leakage to ground, perform test while system is active and at rest)",
    "answer": null,
    "note": ""
  },
  {
    "id": "13",
    "text":
      "Relay Conditions (securely mounted, contact condition, no rust or debris in housing, properly identified, corresponds to the circuit plan)",
    "answer": null,
    "note": ""
  },
  {
    "id": "14",
    "text":
      "Design Plan Conditions (complete, accurate, legible, up to date)",
    "answer": null,
    "note": ""
  },
  {
    "id": "15a",
    "text":
      "Signage - Railway Responsibility (SRCS, # tracks, emergency notification, etc.)",
    "answer": null,
    "note": ""
  },
  {
    "id": "15b",
    "text":
      "Signage - Road Authority Responsibility (Railway Crossing Ahead, Advisory Speed tab, Prepare to Stop at Railway Crossing, etc.)",
    "answer": null,
    "note": ""
  },
  {
    "id": "16a",
    "text": "Railway Sightlines (at 5m, note quadrants)",
    "answer": null,
    "note": ""
  },
  {
    "id": "17a",
    "text": "Crossing Surface Condition",
    "answer": null,
    "note": ""
  },
  {
    "id": "17b",
    "text": "Crossing Surface Width",
    "answer": null,
    "note": ""
  },
  {
    "id": "17c",
    "text":
      "Crossing Surface Flangeway (width, depth, condition of the flangeway)",
    "answer": null,
    "note": ""
  },
  {
    "id": "17d",
    "text": "Crossing Road Approach Conditions",
    "answer": null,
    "note": ""
  },
  {
    "id": "17e",
    "text": "Crossing Road Approach Geometery",
    "answer": null,
    "note": ""
  },
  {
    "id": "17f",
    "text":
      "Location of Grade Crossing (Restrictions on the proximity of intersections and entranceways to grade crossings)",
    "answer": null,
    "note": ""
  },
  {
    "id": "17g",
    "text":
      "Stopping on the crossing surface (queuing or stopping on crossing surface issues)",
    "answer": null,
    "note": ""
  },
  {
    "id": "18",
    "text":
      "Unnecessary Activation of Warning System (Equipment left standing in a manner that causes the activation of the warning system at a public grade crossing other than for the purpose of crossing that grade crossing)",
    "answer": null,
    "note": ""
  },
  {
    "id": "19",
    "text":
      "Obstruction of Grade Crossing (equipment left standing on a crossing surface or for switching operations for more than five minutes in a manner that obstructs a public grade crossing or activates the gates when vehicle or pedestrian traffic waiting to cross)",
    "answer": null,
    "note": ""
  },
  {
    "id": "20",
    "text":
      "Evidence of Trespassing (cut fence, worn footpath, witnessed event)",
    "answer": null,
    "note": ""
  },
  {
    "id": "21",
    "text":
      "Whistle Cessation Concern (introduced since GCR but does not meet requirements, or pre-GCR but is concern for safety)",
    "answer": null,
    "note": ""
  },
  {
    "id": "22a",
    "text":
      "Persons performing duties did not appear familiar with equipment/components within their responsibility",
    "answer": null,
    "note": ""
  },
  {
    "id": "22b",
    "text":
      "Persons performing duties did not appear familiar with the railways inspection and testing requirements, and other procedures",
    "answer": null,
    "note": ""
  },
  {
    "id": "22c",
    "text":
      "Persons performing duties did not appear to have an understanding of safety requirements during testing, and/or how to protect safe railway operations during the undertaking of their duties",
    "answer": null,
    "note": ""
  },
  {
    "id": "22d",
    "text":
      "performing duties were not able to correctly answer all questions and perform all tasks requested by the RSI at the time of inspection, and/or did not appear confident and knowledgeable when implementing them",
    "answer": null,
    "note": ""
  },
  {
    "id": "23",
    "text":
      "Timetable, Logbook, Maintenance Manuals (all applicable information available, complete, correct)",
    "answer": null,
    "note": ""
  },
  {
    "id": "24",
    "text": "Light Units Voltage (within threshold)",
    "answer": null,
    "note": ""
  },
  {
    "id": "25",
    "text": "Software and Calibration",
    "answer": null,
    "note": ""
  },
  {
    "id": "26",
    "text": "Operational Tests (post repair/replacement)",
    "answer": null,
    "note": ""
  },
  {
    "id": "27",
    "text":
      "Switch Circuit Controller (Adjustment and condition, centering device condition)",
    "answer": null,
    "note": ""
  },
  {
    "id": "28",
    "text":
      "Condition of Structures (masts, ladders, platforms, bases, foundation, junction boxes)",
    "answer": null,
    "note": ""
  },
  {
    "id": "29",
    "text":
      "External Condition of Housing (foundations, door, locks, free of debris)",
    "answer": null,
    "note": ""
  },
  {
    "id": "30",
    "text":
      "Internal Condition of Housing (clean, sealed, ventilation, moisture, no evidence of infestation)",
    "answer": null,
    "note": ""
  },
  {
    "id": "31",
    "text":
      "Location Conditions (equipment, tagging, wiring, lighting arresters)",
    "answer": null,
    "note": ""
  },
  {
    "id": "32",
    "text":
      "Clearance - Vertical/Horizontal (light units, cantilever, gate)",
    "answer": null,
    "note": ""
  },
  {
    "id": "33",
    "text":
      "Operational Issues (queuing, departure time, hidden train operation, two+ tracks, standing railway equipment, crossing not used)",
    "answer": null,
    "note": ""
  },
  {
    "id": "34",
    "text":
      "Cables and Line Wires (pole line, aerial, underground wire, cable clearance)",
    "answer": null,
    "note": ""
  },
  {
    "id": "35",
    "text":
      "Misc. issues - Railway (other safety Issues of Railway responsibility)",
    "answer": null,
    "note": ""
  },
  {
    "id": "36",
    "text":
      "Misc. issues - Road Authority (other safety issues of Road Authority responsibility)",
    "answer": null,
    "note": ""
  }
]